[
  {"id": "computer-principles", "year": 1, "semester": 1, "title_ar": "مبادئ عمل الحاسوب", "title_en": "Computer Principles", "status": "none", "summary_md": "courses/computer-principles.md"},
  {"id": "calculus-1", "year": 1, "semester": 1, "title_ar": "تحليل 1", "title_en": "Calculus 1", "status": "none", "summary_md": "courses/calculus-1.md"},
  {"id": "physics-1", "year": 1, "semester": 1, "title_ar": "فيزياء 1", "title_en": "Physics 1", "status": "none", "summary_md": "courses/physics-1.md"},
  {"id": "discrete-math", "year": 1, "semester": 1, "title_ar": "رياضيات متقطعة", "title_en": "Discrete Mathematics", "status": "reviewed", "summary_md": "courses/discrete-math.md"},
  {"id": "language-1", "year": 1, "semester": 1, "title_ar": "لغة 1", "title_en": "Language 1", "status": "none", "summary_md": "courses/language-1.md"},
  {"id": "programming-1", "year": 1, "semester": 1, "title_ar": "برمجة 1", "title_en": "Programming 1", "status": "reviewed", "summary_md": "courses/programming-1.md"},

  {"id": "linear-algebra", "year": 1, "semester": 2, "title_ar": "الجبر الخطي", "title_en": "Linear Algebra", "status": "reviewed", "summary_md": "courses/linear-algebra.md"},
  {"id": "calculus-2", "year": 1, "semester": 2, "title_ar": "التحليل 2", "title_en": "Calculus 2", "status": "none", "summary_md": "courses/calculus-2.md"},
  {"id": "electrical-circuits", "year": 1, "semester": 2, "title_ar": "الدارات الكهربائية", "title_en": "Electrical Circuits", "status": "none", "summary_md": "courses/electrical-circuits.md"},
  {"id": "physics-2", "year": 1, "semester": 2, "title_ar": "فيزياء 2", "title_en": "Physics 2", "status": "none", "summary_md": "courses/physics-2.md"},
  {"id": "arabic", "year": 1, "semester": 2, "title_ar": "اللغة العربية", "title_en": "Arabic", "status": "none", "summary_md": "courses/arabic.md"},
  {"id": "programming-2", "year": 1, "semester": 2, "title_ar": "برمجة 2", "title_en": "Programming 2", "status": "none", "summary_md": "courses/programming-2.md"},

  {"id": "calculus-3", "year": 2, "semester": 1, "title_ar": "التحليل 3", "title_en": "Calculus 3", "status": "none", "summary_md": "courses/calculus-3.md"},
  {"id": "numerical-analysis-1", "year": 2, "semester": 1, "title_ar": "التحليل العددي 1", "title_en": "Numerical Analysis 1", "status": "none", "summary_md": "courses/numerical-analysis-1.md"},
  {"id": "programming-3", "year": 2, "semester": 1, "title_ar": "برمجة 3", "title_en": "Programming 3", "status": "none", "summary_md": "courses/programming-3.md"},
  {"id": "electronics", "year": 2, "semester": 1, "title_ar": "إلكترونيات", "title_en": "Electronics", "status": "none", "summary_md": "courses/electronics.md"},
  {"id": "probability", "year": 2, "semester": 1, "title_ar": "احتمالات", "title_en": "Probability", "status": "none", "summary_md": "courses/probability.md"},
  {"id": "mathematical-programming", "year": 2, "semester": 1, "title_ar": "برمجة رياضية", "title_en": "Mathematical Programming", "status": "none", "summary_md": "courses/mathematical-programming.md"},

  {"id": "numerical-analysis-2", "year": 2, "semester": 2, "title_ar": "التحليل العددي 2", "title_en": "Numerical Analysis 2", "status": "none", "summary_md": "courses/numerical-analysis-2.md"},
  {"id": "communication-skills", "year": 2, "semester": 2, "title_ar": "مهارات التواصل", "title_en": "Communication Skills", "status": "none", "summary_md": "courses/communication-skills.md"},
  {"id": "algorithms-1", "year": 2, "semester": 2, "title_ar": "خوارزميات 1", "title_en": "Algorithms 1", "status": "reviewed", "summary_md": "courses/algorithms-1.md"},
  {"id": "statistics", "year": 2, "semester": 2, "title_ar": "إحصاء", "title_en": "Statistics", "status": "none", "summary_md": "courses/statistics.md"},
  {"id": "logic-circuits", "year": 2, "semester": 2, "title_ar": "دارات منطقية", "title_en": "Logic Circuits", "status": "none", "summary_md": "courses/logic-circuits.md"},

  {"id": "computer-graphics", "year": 3, "semester": 1, "title_ar": "رسوميات حاسوبية", "title_en": "Computer Graphics", "status": "none", "summary_md": "courses/رسومات-حاسوبية.md"},
  {"id": "algorithms-2", "year": 3, "semester": 1, "title_ar": "خوارزميات 2", "title_en": "Algorithms 2", "status": "none", "summary_md": "courses/خوارزميات-2.md"},
  {"id": "graph-theory", "year": 3, "semester": 1, "title_ar": "نظرية المخططات", "title_en": "Graph Theory", "status": "reviewed", "summary_md": "courses/graph-theory.md"},
  {"id": "microprocessor", "year": 3, "semester": 1, "title_ar": "معالج مصغر", "title_en": "Microprocessor", "status": "none", "summary_md": "courses/معالج-مصغر.md"},
  {"id": "signal-processing", "year": 3, "semester": 1, "title_ar": "معالجة الإشارة", "title_en": "Signal Processing", "status": "none", "summary_md": "courses/معالجة-الإشارة.md"},
  {"id": "information-theory", "year": 3, "semester": 1, "title_ar": "نظرية المعلومات", "title_en": "Information Theory", "status": "none", "summary_md": "courses/نظرية-المعلومات.md"},
  {"id": "databases-1", "year": 3, "semester": 1, "title_ar": "قواعد المعطيات 1", "title_en": "Databases 1", "status": "reviewed", "summary_md": "courses/databases-1.md"},

  {"id": "ai-fundamentals", "year": 3, "semester": 2, "title_ar": "مبادئ الذكاء الاصطناعي", "title_en": "AI Fundamentals", "status": "none", "summary_md": "courses/ذكاء-اصطناعي-مبادئ.md"},
  {"id": "algorithms-3", "year": 3, "semester": 2, "title_ar": "خوارزميات 3", "title_en": "Algorithms 3", "status": "none", "summary_md": "courses/خوارزميات-3.md"},
  {"id": "digital-communications", "year": 3, "semester": 2, "title_ar": "اتصالات تشابهية ورقمية", "title_en": "Digital Communications", "status": "none", "summary_md": "courses/اتصالات-تشابهية-رقمية.md"},
  {"id": "computer-organization-1", "year": 3, "semester": 2, "title_ar": "بنية وتنظيم الحاسب 1", "title_en": "Computer Organization 1", "status": "none", "summary_md": "courses/بنية-تنظيم-الحاسب-1.md"},
  {"id": "computer-networks", "year": 3, "semester": 2, "title_ar": "شبكات حاسوبية", "title_en": "Computer Networks", "status": "none", "summary_md": "courses/شبكات-حاسوبية.md"},
  {"id": "formal-languages", "year": 3, "semester": 2, "title_ar": "لغات صورية", "title_en": "Formal Languages", "status": "none", "summary_md": "courses/لغات-صورية.md"},
  {"id": "software-engineering-1", "year": 3, "semester": 2, "title_ar": "هندسة البرمجيات 1", "title_en": "Software Engineering 1", "status": "none", "summary_md": "courses/هندسة-البرمجيات-1.md"},

  {"id": "automata-theory", "year": 4, "semester": 1, "title_ar": "نظرية الأرتال", "title_en": "Automata Theory", "status": "none", "summary_md": "courses/نظرية-الأرتال.md"},
  {"id": "operating-systems-1", "year": 4, "semester": 1, "title_ar": "نظم تشغيل 1", "title_en": "Operating Systems 1", "status": "none", "summary_md": "courses/نظم-تشغيل-1.md"},
  {"id": "compiler-design", "year": 4, "semester": 1, "title_ar": "تصميم المترجمات", "title_en": "Compiler Design", "status": "none", "summary_md": "courses/تصميم-المترجمات.md"},
  {"id": "databases-2", "year": 4, "semester": 1, "title_ar": "قواعد المعطيات 2", "title_en": "Databases 2", "status": "none", "summary_md": "courses/قواعد-المعطيات-2.md"},
  {"id": "computer-architecture-2", "year": 4, "semester": 1, "title_ar": "بنية وتنظيم الحواسيب 2", "title_en": "Computer Architecture 2", "status": "none", "summary_md": "courses/بنية-تنظيم-الحواسيب-2.md"},
  {"id": "advanced-networks", "year": 4, "semester": 1, "title_ar": "شبكات متقدمة", "title_en": "Advanced Networks", "status": "none", "summary_md": "courses/شبكات-متقدمة.md"},
  {"id": "multimedia-systems", "year": 4, "semester": 1, "title_ar": "نظم وسائط متعددة", "title_en": "Multimedia Systems", "status": "none", "summary_md": "courses/نظم-وسائط-متعددة.md"},
  {"id": "logic-programming", "year": 4, "semester": 1, "title_ar": "برمجة منطقية", "title_en": "Logic Programming", "status": "none", "summary_md": "courses/برمجة-منطقية.md"},
  {"id": "operations-research", "year": 4, "semester": 1, "title_ar": "بحوث عمليات", "title_en": "Operations Research", "status": "none", "summary_md": "courses/بحوث-عمليات.md"},

  {"id": "marketing-project-management", "year": 4, "semester": 2, "title_ar": "تسويق وإدارة مشاريع", "title_en": "Marketing & Project Management", "status": "none", "summary_md": "courses/تسويق-وإدارة-مشاريع.md"},
  {"id": "neural-networks", "year": 4, "semester": 2, "title_ar": "شبكات عصبونية ومنطق الترجيح", "title_en": "Neural Networks & Fuzzy Logic", "status": "none", "summary_md": "courses/شبكات-عصبونية-منطق-الترجيح.md"},
  {"id": "operating-systems-2", "year": 4, "semester": 2, "title_ar": "نظم تشغيل 2", "title_en": "Operating Systems 2", "status": "none", "summary_md": "courses/نظم-تشغيل-2.md"},
  {"id": "robotics", "year": 4, "semester": 2, "title_ar": "روبوتيكا", "title_en": "Robotics", "status": "none", "summary_md": "courses/روبوتيكا.md"},
  {"id": "information-security", "year": 4, "semester": 2, "title_ar": "أمن المعلومات", "title_en": "Information Security", "status": "none", "summary_md": "courses/أمن-المعلومات.md"},
  {"id": "software-engineering-2", "year": 4, "semester": 2, "title_ar": "هندسة البرمجيات 2", "title_en": "Software Engineering 2", "status": "none", "summary_md": "courses/هندسة-البرمجيات-2.md"},
  {"id": "programmable-digital-systems", "year": 4, "semester": 2, "title_ar": "نظم رقمية مبرمجة", "title_en": "Programmable Digital Systems", "status": "none", "summary_md": "courses/نظم-رقمية-مبرمجة.md"},
  {"id": "parallel-programming", "year": 4, "semester": 2, "title_ar": "برمجة تفرعية", "title_en": "Parallel Programming", "status": "none", "summary_md": "courses/برمجة-تفرعية.md"},
  {"id": "internet-applications", "year": 4, "semester": 2, "title_ar": "تطبيقات الإنترنت", "title_en": "Internet Applications", "status": "none", "summary_md": "courses/تطبيقات-الانترنت.md"},

  {"id": "network-security", "year": 5, "semester": 1, "title_ar": "أمن الشبكات", "title_en": "Network Security", "status": "none", "summary_md": "courses/أمن-الشبكات.md"},
  {"id": "software-engineering-3", "year": 5, "semester": 1, "title_ar": "هندسة البرمجيات 3", "title_en": "Software Engineering 3", "status": "none", "summary_md": "courses/هندسة-البرمجيات-3.md"},
  {"id": "plc-programming", "year": 5, "semester": 1, "title_ar": "تحكم منطقي مبرمج PLC", "title_en": "PLC Programming", "status": "none", "summary_md": "courses/تحكم-منطقي-مبرمج-plc.md"},
  {"id": "expert-systems", "year": 5, "semester": 1, "title_ar": "نظم خبيرة", "title_en": "Expert Systems", "status": "none", "summary_md": "courses/نظم-خبرة.md"},
  {"id": "computer-vision", "year": 5, "semester": 1, "title_ar": "رؤية حاسوبية", "title_en": "Computer Vision", "status": "none", "summary_md": "courses/رؤية-حاسوبية.md"},
  {"id": "modeling-simulation", "year": 5, "semester": 1, "title_ar": "نمذجة ومحاكاة", "title_en": "Modeling & Simulation", "status": "none", "summary_md": "courses/نمذجة-محاكاة.md"},
  {"id": "quality-reliability", "year": 5, "semester": 1, "title_ar": "جودة ووثوقية", "title_en": "Quality & Reliability", "status": "none", "summary_md": "courses/جودة-وثوقية.md"},
  {"id": "distributed-systems", "year": 5, "semester": 1, "title_ar": "نظم موزعة", "title_en": "Distributed Systems", "status": "none", "summary_md": "courses/نظم-موزعة.md"},

  {"id": "nlp", "year": 5, "semester": 2, "title_ar": "معالجة لغات طبيعية", "title_en": "Natural Language Processing", "status": "none", "summary_md": "courses/معالجة-لغات-طبيعية.md"},
  {"id": "data-mining", "year": 5, "semester": 2, "title_ar": "تنقيب المعطيات", "title_en": "Data Mining", "status": "none", "summary_md": "courses/تنقيب-المعطيات.md"},
  {"id": "production-management", "year": 5, "semester": 2, "title_ar": "إدارة نظم إنتاجية", "title_en": "Production Operations Management", "status": "none", "summary_md": "courses/إدارة-نظم-إنتاجية.md"},
  {"id": "real-time-systems", "year": 5, "semester": 2, "title_ar": "نظم الزمن الحقيقي", "title_en": "Real-Time Systems", "status": "none", "summary_md": "courses/نظم-الزمن-ال-real.md"},
  {"id": "wireless-networks", "year": 5, "semester": 2, "title_ar": "الشبكات اللاسلكية", "title_en": "Wireless Networks", "status": "none", "summary_md": "courses/الشبكات-اللاسلكية.md"}
]